persistent_code/__init__.py
persistent_code/__main__.py
persistent_code/code_analyzer.py
persistent_code/config.py
persistent_code/context_assembler.py
persistent_code/knowledge_graph.py
persistent_code/llama_index_manager.py
persistent_code/mcp_server.py
tests/__init__.py
tests/test_knowledge_graph.py
iflow_mcp_sparshdrolia_persistent_code-0.1.2.dist-info/METADATA
iflow_mcp_sparshdrolia_persistent_code-0.1.2.dist-info/WHEEL
iflow_mcp_sparshdrolia_persistent_code-0.1.2.dist-info/entry_points.txt
iflow_mcp_sparshdrolia_persistent_code-0.1.2.dist-info/top_level.txt
iflow_mcp_sparshdrolia_persistent_code-0.1.2.dist-info/RECORD
