Metadata-Version: 2.4
Name: iflow-mcp_sparshdrolia_persistent-code
Version: 0.1.2
Summary: An MCP server for maintaining code knowledge across LLM chat sessions
Home-page: https://github.com/yourusername/persistent-code-mcp
Author: Your Name
Author-email: Your Name <your.email@example.com>
License: MIT
Project-URL: Homepage, https://github.com/yourusername/persistent-code-mcp
Project-URL: Repository, https://github.com/yourusername/persistent-code-mcp
Classifier: Development Status :: 3 - Alpha
Classifier: Intended Audience :: Developers
Classifier: License :: OSI Approved :: MIT License
Classifier: Programming Language :: Python :: 3
Classifier: Programming Language :: Python :: 3.10
Classifier: Programming Language :: Python :: 3.11
Requires-Python: >=3.10
Requires-Dist: mcp>=1.2.0
Requires-Dist: llama-index-core>=0.9.0
Requires-Dist: llama-index>=0.10.0
Requires-Dist: llama-index-embeddings-huggingface>=0.1.0
Requires-Dist: transformers>=4.34.0
Requires-Dist: networkx>=3.1
Requires-Dist: sentence-transformers>=2.2.0
Requires-Dist: pydantic>=2.0.0
Requires-Dist: sqlalchemy>=2.0.0
Requires-Dist: fastapi>=0.103.0
Requires-Dist: uvicorn>=0.23.0
Requires-Dist: python-dotenv>=1.0.0
Dynamic: author
Dynamic: home-page
Dynamic: requires-python
